{
	"pages": [{
			"path": "pages/training/training",
			"style": {
				"navigationBarTitleText": "",
				"nvue": true,
				"app-plus": {
					"titleNView": {
						"titleText": false
					}
				}
			}
		},
		{
			"path": "pages/actions/actions",
			"style": {
				"navigationBarTitleText": "",
				"nvue": true,
				"app-plus": {
					"titleNView": {
						"titleText": false
					}
				}
			}
		},
		{
			"path": "pages/calendar/calendar",
			"style": {
				"navigationBarTitleText": "",
				"nvue": true,
				"app-plus": {
					"titleNView": {
						"titleText": false
					}
				}
			}
		},
		{
			"path": "pages/profile/profile",
			"style": {
				"navigationBarTitleText": "",
				"nvue": true,
				"app-plus": {
					"titleNView": {
						"titleText": false
					}
				}
			}
		},
		{
			"path": "pages/training-session/training-session",
			"style": {
				"navigationBarTitleText": "训练会话",
				"nvue": true,
				"app-plus": {
					"bounce": "none",
					"titleNView": {
						"backgroundColor": "#F8F8F8",
						"titleColor": "#333333"
					}
				}
			}
		},
		{
			"path": "pages/example/index",
			"style": {
				"navigationBarTitleText": "",
				"nvue": true,
				"app-plus": {
					"titleNView": {
						"titleText": false
					}
				}
			}
		}
	],
	"globalStyle": {
		"navigationBarTextStyle": "black",
		"navigationBarTitleText": "uni-app",
		"navigationBarBackgroundColor": "#F8F8F8",
		"backgroundColor": "#F8F8F8"
	},
	"tabBar": {
		"color": "#7A7E83",
		"selectedColor": "#0A84FF",
		"borderStyle": "black",
		"backgroundColor": "#ffffff",
		"height": "50px",
		"fontSize": "10px",
		"iconWidth": "24px",
		"spacing": "3px",
		"list": [{
				"pagePath": "pages/training/training",
				"text": "训练"
			},
			{
				"pagePath": "pages/actions/actions",
				"text": "动作"
			},
			{
				"pagePath": "pages/calendar/calendar",
				"text": "日历"
			},
			{
				"pagePath": "pages/profile/profile",
				"text": "我的"
			}
		]
	},
	"app-plus": {
		"nvueCompiler": "uni-app",
		"renderer": "native"
	}
}
